nummethvera
