Metadata-Version: 2.1
Name: nummethvera
Version: 0.2.0
Summary: Numeric methods library
Home-page: https://github.com/dthseemsbttr/numericmethodsdths
Author: Vera Korotkova
Author-email: verakorotkova10@mail.ru
License: MIT
Platform: UNKNOWN
License-File: LICENSE
